EdaSpiffWorkflow_Aadesh_G/__init__.py
EdaSpiffWorkflow_Aadesh_G/exceptions.py
EdaSpiffWorkflow_Aadesh_G/navigation.py
EdaSpiffWorkflow_Aadesh_G/operators.py
EdaSpiffWorkflow_Aadesh_G/task.py
EdaSpiffWorkflow_Aadesh_G/version.py
EdaSpiffWorkflow_Aadesh_G/workflow.py
EdaSpiffWorkflow_Aadesh_G/bpmn/FeelLikeScriptEngine.py
EdaSpiffWorkflow_Aadesh_G/bpmn/PythonScriptEngine.py
EdaSpiffWorkflow_Aadesh_G/bpmn/__init__.py
EdaSpiffWorkflow_Aadesh_G/bpmn/workflow.py
EdaSpiffWorkflow_Aadesh_G/bpmn/parser/BpmnParser.py
EdaSpiffWorkflow_Aadesh_G/bpmn/parser/ProcessParser.py
EdaSpiffWorkflow_Aadesh_G/bpmn/parser/TaskParser.py
EdaSpiffWorkflow_Aadesh_G/bpmn/parser/ValidationException.py
EdaSpiffWorkflow_Aadesh_G/bpmn/parser/__init__.py
EdaSpiffWorkflow_Aadesh_G/bpmn/parser/event_parsers.py
EdaSpiffWorkflow_Aadesh_G/bpmn/parser/task_parsers.py
EdaSpiffWorkflow_Aadesh_G/bpmn/parser/util.py
EdaSpiffWorkflow_Aadesh_G/bpmn/serializer/BpmnSerializer.py
EdaSpiffWorkflow_Aadesh_G/bpmn/serializer/CompactWorkflowSerializer.py
EdaSpiffWorkflow_Aadesh_G/bpmn/serializer/Packager.py
EdaSpiffWorkflow_Aadesh_G/bpmn/serializer/__init__.py
EdaSpiffWorkflow_Aadesh_G/bpmn/serializer/bpmn_converters.py
EdaSpiffWorkflow_Aadesh_G/bpmn/serializer/dictionary.py
EdaSpiffWorkflow_Aadesh_G/bpmn/serializer/task_spec_converters.py
EdaSpiffWorkflow_Aadesh_G/bpmn/serializer/workflow.py
EdaSpiffWorkflow_Aadesh_G/bpmn/serializer/workflow_spec_converter.py
EdaSpiffWorkflow_Aadesh_G/bpmn/specs/BpmnProcessSpec.py
EdaSpiffWorkflow_Aadesh_G/bpmn/specs/BpmnSpecMixin.py
EdaSpiffWorkflow_Aadesh_G/bpmn/specs/ExclusiveGateway.py
EdaSpiffWorkflow_Aadesh_G/bpmn/specs/InclusiveGateway.py
EdaSpiffWorkflow_Aadesh_G/bpmn/specs/ManualTask.py
EdaSpiffWorkflow_Aadesh_G/bpmn/specs/MultiInstanceTask.py
EdaSpiffWorkflow_Aadesh_G/bpmn/specs/NoneTask.py
EdaSpiffWorkflow_Aadesh_G/bpmn/specs/ParallelGateway.py
EdaSpiffWorkflow_Aadesh_G/bpmn/specs/ScriptTask.py
EdaSpiffWorkflow_Aadesh_G/bpmn/specs/SubWorkflowTask.py
EdaSpiffWorkflow-0.0.2.dist-info/LICENSE
EdaSpiffWorkflow-0.0.2.dist-info/METADATA
EdaSpiffWorkflow-0.0.2.dist-info/WHEEL
EdaSpiffWorkflow-0.0.2.dist-info/top_level.txt
EdaSpiffWorkflow-0.0.2.dist-info/RECORD
