Metadata-Version: 2.1
Name: EdaSpiffWorkflow
Version: 0.0.2
Summary: A WF Manager for EDA with Spiff
Home-page: https://github.com/sartography/SpiffWorkflow
Author: Sartography||AG
Author-email: Aadesh Gurav <guravaadesh99@gmail.com>
License: lGPLv2
Keywords: spiff workflow bpmn engine
Classifier: Programming Language :: Python :: 3
Classifier: License :: OSI Approved :: MIT License
Classifier: Operating System :: OS Independent
Requires-Python: >=3.6
License-File: LICENSE
Requires-Dist: configparser
Requires-Dist: lxml
Requires-Dist: celery
Requires-Dist: dateparser
Requires-Dist: pytz
